[
  { "key": "canonici", "value": "canonico" },
  { "key": "cavalieri", "value": "cavaliere" },
  { "key": "colonnelli", "value": "colonnello" },
  { "key": "commissari", "value": "commissario" },
  { "key": "conti", "value": "conte" },
  { "key": "domine", "value": "domina" },
  { "key": "domini", "value": "domino" },
  { "key": "gentildonne", "value": "gentildonna" },
  { "key": "governatori", "value": "governatore" },
  { "key": "homini", "value": "homo" },
  { "key": "homini ser", "value": "homo ser" },
  { "key": "illustrissime", "value": "illustrissima" },
  { "key": "illustrissime gentildonne", "value": "illustrissima gentildonna" },
  { "key": "illustrissime monache", "value": "illustrissima monaca" },
  { "key": "illustrissimi", "value": "illustrissimo" },
  { "key": "illustrissimi signori", "value": "illustrissimo signor" },
  { "key": "monache", "value": "monaca" },
  { "key": "monache domine", "value": "monaca domina" },
  { "key": "nobil domine", "value": "nobil domina" },
  { "key": "nobil homini", "value": "nobil homo" },
  { "key": "nobil homini conti", "value": "nobil homo conte" },
  { "key": "nobil homini conti", "value": "nobil homo conte" },
  { "key": "nobil homini ser", "value": "nobil homo ser" },
  { "key": "nobil homo ser", "value": "nobil homo ser" },
  { "key": "nobili", "value": "nobil" },
  { "key": "padri gesuiti", "value": "padre gesuita" },
  { "key": "procuratori di san marco", "value": "procuratore di san marco" },
  { "key": "rappresentanti", "value": "rappresentante" },
  { "key": "reverende", "value": "reverenda" },
  { "key": "reverende monache", "value": "reverenda monaca" },
  { "key": "reverendi", "value": "reverendo" },
  { "key": "reverendi don", "value": "reverendo don" },
  { "key": "reverendi padri", "value": "reverendo padre" },
  { "key": "reverendi signori", "value": "reverendo signor" },
  { "key": "segretari", "value": "segretario" },
  { "key": "signori", "value": "signor" }
]
